LICENSE
MANIFEST.in
README.md
setup.py
friction/__init__.py
friction/application.wsgi
friction/library.py
friction.egg-info/PKG-INFO
friction.egg-info/SOURCES.txt
friction.egg-info/dependency_links.txt
friction.egg-info/requires.txt
friction.egg-info/top_level.txt
friction/static/friction.css
friction/static/friction.js
friction/static/lib/photoswipe/LICENSE
friction/static/lib/photoswipe/photoswipe-ui-default.js
friction/static/lib/photoswipe/photoswipe.css
friction/static/lib/photoswipe/photoswipe.js
friction/static/lib/photoswipe/default-skin/default-skin.css
friction/static/lib/photoswipe/default-skin/default-skin.png
friction/static/lib/photoswipe/default-skin/default-skin.svg
friction/static/lib/photoswipe/default-skin/preloader.gif
friction/templates/viewer.html
scripts/friction
scripts/friction-ui