Metadata-Version: 2.1
Name: friction
Version: 0.9
Summary: a browser-based gallery viewer tailored for viewing large collections of pornographic manga
Home-page: https://github.com/tinruufu/friction
Author: ティン・ルーフ
Author-email: tinruufu+pypi@gmail.com
License: MIT
Platform: any
Classifier: Intended Audience :: End Users/Desktop
Classifier: Topic :: Multimedia :: Graphics :: Viewers
Classifier: License :: OSI Approved :: MIT License
Classifier: Programming Language :: Python :: 3 :: Only
